Bootstrap3ShiyongjiaochengWaiBowang/README.md
Bootstrap3ShiyongjiaochengWaiBowang/__init__.py
Bootstrap3ShiyongjiaochengWaiBowang/__main__.py
Bootstrap3ShiyongjiaochengWaiBowang/file.epub
Bootstrap3ShiyongjiaochengWaiBowang/index.html
Bootstrap3ShiyongjiaochengWaiBowang/css/__init__.py
Bootstrap3ShiyongjiaochengWaiBowang/css/annotations.css
Bootstrap3ShiyongjiaochengWaiBowang/css/main.css
Bootstrap3ShiyongjiaochengWaiBowang/css/normalize.css
Bootstrap3ShiyongjiaochengWaiBowang/css/popup.css
Bootstrap3ShiyongjiaochengWaiBowang/font/__init__.py
Bootstrap3ShiyongjiaochengWaiBowang/font/fontello.eot
Bootstrap3ShiyongjiaochengWaiBowang/font/fontello.svg
Bootstrap3ShiyongjiaochengWaiBowang/font/fontello.ttf
Bootstrap3ShiyongjiaochengWaiBowang/font/fontello.woff
Bootstrap3ShiyongjiaochengWaiBowang/img/__init__.py
Bootstrap3ShiyongjiaochengWaiBowang/img/annotator-glyph-sprite.png
Bootstrap3ShiyongjiaochengWaiBowang/img/annotator-icon-sprite.png
Bootstrap3ShiyongjiaochengWaiBowang/img/apple-touch-icon.png
Bootstrap3ShiyongjiaochengWaiBowang/img/cancelfullscreen.png
Bootstrap3ShiyongjiaochengWaiBowang/img/close.png
Bootstrap3ShiyongjiaochengWaiBowang/img/fullscreen.png
Bootstrap3ShiyongjiaochengWaiBowang/img/loader.gif
Bootstrap3ShiyongjiaochengWaiBowang/img/menu-icon.png
Bootstrap3ShiyongjiaochengWaiBowang/img/save.png
Bootstrap3ShiyongjiaochengWaiBowang/img/saved.png
Bootstrap3ShiyongjiaochengWaiBowang/img/settings-s.png
Bootstrap3ShiyongjiaochengWaiBowang/img/settings.png
Bootstrap3ShiyongjiaochengWaiBowang/img/star.png
Bootstrap3ShiyongjiaochengWaiBowang/js/__init__.py
Bootstrap3ShiyongjiaochengWaiBowang/js/epub.js
Bootstrap3ShiyongjiaochengWaiBowang/js/epub.min.js
Bootstrap3ShiyongjiaochengWaiBowang/js/epub.min.map
Bootstrap3ShiyongjiaochengWaiBowang/js/hooks.min.js
Bootstrap3ShiyongjiaochengWaiBowang/js/hooks.min.map
Bootstrap3ShiyongjiaochengWaiBowang/js/reader.js
Bootstrap3ShiyongjiaochengWaiBowang/js/reader.js.map
Bootstrap3ShiyongjiaochengWaiBowang/js/reader.min.js
bootstrap3_shiyongjiaocheng_wai_bowang-2024.3.4.0.dist-info/METADATA
bootstrap3_shiyongjiaocheng_wai_bowang-2024.3.4.0.dist-info/WHEEL
bootstrap3_shiyongjiaocheng_wai_bowang-2024.3.4.0.dist-info/entry_points.txt
bootstrap3_shiyongjiaocheng_wai_bowang-2024.3.4.0.dist-info/top_level.txt
bootstrap3_shiyongjiaocheng_wai_bowang-2024.3.4.0.dist-info/RECORD
